ticket_auth/__init__.py
ticket_auth/exception.py
ticket_auth/ticket_factory.py
ticket_auth-0.1.4.dist-info/DESCRIPTION.rst
ticket_auth-0.1.4.dist-info/METADATA
ticket_auth-0.1.4.dist-info/RECORD
ticket_auth-0.1.4.dist-info/WHEEL
ticket_auth-0.1.4.dist-info/metadata.json
ticket_auth-0.1.4.dist-info/top_level.txt
