Metadata-Version: 1.1
Name: ticket-auth
Version: 0.1.4
Summary: Ticket authentication system similar to mod_auth_tkt used by Apache
Home-page: https://github.com/gnarlychicken/ticket_auth
Author: Gnarly Chicken
Author-email: gnarlychicken@gmx.com
License: MIT
Keywords: mod_auth_tkt authentication session ticket
Platform: UNKNOWN
Classifier: Development Status :: 3 - Alpha
Classifier: Intended Audience :: Developers
Classifier: Topic :: Internet :: WWW/HTTP :: Session
Classifier: License :: OSI Approved :: MIT License
Classifier: Programming Language :: Python :: 3 :: Only
Classifier: Programming Language :: Python :: 3.4
Classifier: Programming Language :: Python :: 3.5
